deirokay/__init__.py
deirokay/__version__.py
deirokay/_typing.py
deirokay/_utils.py
deirokay/backend.py
deirokay/enums.py
deirokay/exceptions.py
deirokay/fs.py
deirokay/history_template.py
deirokay/profiler.py
deirokay/validator.py
deirokay/airflow/__init__.py
deirokay/airflow/deirokay_operator.py
deirokay/parser/__init__.py
deirokay/parser/loader.py
deirokay/parser/reader/__init__.py
deirokay/parser/reader/dask_reader.py
deirokay/parser/reader/pandas_reader.py
deirokay/parser/treaters/__init__.py
deirokay/parser/treaters/multibackend.py
deirokay/parser/treaters/builtin/__init__.py
deirokay/parser/treaters/builtin/base_treater.py
deirokay/parser/treaters/builtin/boolean_treater.py
deirokay/parser/treaters/builtin/date_treater.py
deirokay/parser/treaters/builtin/datetime64_treater.py
deirokay/parser/treaters/builtin/decimal_treater.py
deirokay/parser/treaters/builtin/float_treater.py
deirokay/parser/treaters/builtin/integer_treater.py
deirokay/parser/treaters/builtin/numeric_treater.py
deirokay/parser/treaters/builtin/string_treater.py
deirokay/parser/treaters/builtin/time_treater.py
deirokay/parser/treaters/builtin/validator.py
deirokay/statements/__init__.py
deirokay/statements/loader.py
deirokay/statements/multibackend.py
deirokay/statements/builtin/__init__.py
deirokay/statements/builtin/base_statement.py
deirokay/statements/builtin/column_expression.py
deirokay/statements/builtin/contain.py
deirokay/statements/builtin/not_null.py
deirokay/statements/builtin/row_count.py
deirokay/statements/builtin/statistic_in_interval.py
deirokay/statements/builtin/unique.py
deirokay-1.2.0.dist-info/LICENSE
deirokay-1.2.0.dist-info/METADATA
deirokay-1.2.0.dist-info/WHEEL
deirokay-1.2.0.dist-info/top_level.txt
deirokay-1.2.0.dist-info/zip-safe
deirokay-1.2.0.dist-info/RECORD
