Metadata-Version: 2.1
Name: deirokay
Version: 1.2.0
Summary: A tool for data profiling and data validation
Home-page: https://github.com/bigdatabr/deirokay
Author: Marcos Bressan
Author-email: marcos.bressan@bigdata.com.br
License: UNKNOWN
Platform: UNKNOWN
Classifier: Programming Language :: Python :: 3
Classifier: Operating System :: OS Independent
Requires-Python: >=3.7
License-File: LICENSE
Requires-Dist: Jinja2 <4,>=2.10.2
Requires-Dist: jq <2,>=1.2.1
Requires-Dist: PyYAML <7,>=5.3.1
Requires-Dist: lazy-import >=v0.2.2
Provides-Extra: dask
Requires-Dist: dask[dataframe] >=2022.1.1 ; extra == 'dask'
Provides-Extra: dev
Requires-Dist: Jinja2 ==2.10.2 ; extra == 'dev'
Requires-Dist: jq ==1.2.1 ; extra == 'dev'
Requires-Dist: PyYAML ==5.3.1 ; extra == 'dev'
Requires-Dist: lazy-import ==v0.2.2 ; extra == 'dev'
Requires-Dist: dask[dataframe] ==2022.1.1 ; extra == 'dev'
Requires-Dist: apache-airflow ==2.0.0 ; extra == 'dev'
Requires-Dist: boto3 ; extra == 'dev'
Requires-Dist: moto <5,>=4.0.0 ; extra == 'dev'
Requires-Dist: pyarrow <15,>=10.0.0 ; extra == 'dev'
Requires-Dist: pytest ; extra == 'dev'
Requires-Dist: pytest-cov ; extra == 'dev'
Requires-Dist: pytest-postgresql ; extra == 'dev'
Requires-Dist: psycopg[binary] ; extra == 'dev'
Requires-Dist: psycopg2[binary] ; extra == 'dev'
Requires-Dist: s3fs ; extra == 'dev'
Requires-Dist: SQLAlchemy ==1.4.52 ; extra == 'dev'
Requires-Dist: pandas ==1.3 ; (python_version < "3.10") and extra == 'dev'
Requires-Dist: markupsafe ==1.1.1 ; (python_version <= "3.7") and extra == 'dev'
Requires-Dist: pandas ==1.4 ; (python_version >= "3.10") and extra == 'dev'
Provides-Extra: pandas
Requires-Dist: pandas <2,>=1.3 ; extra == 'pandas'
Provides-Extra: s3
Requires-Dist: boto3 ; extra == 's3'
Requires-Dist: s3fs ; extra == 's3'
